monodikit/__init__.py
monodikit/analysis/__init__.py
monodikit/analysis/search.py
monodikit/analysis/synopsis.py
monodikit/analysis/utility.py
monodikit/models/__init__.py
monodikit/models/corpus.py
monodikit/models/document.py
monodikit/models/genre_specific.py
monodikit/models/source.py
monodikit/models/utility.py
tests/__init__.py
tests/mock_data.py
tests/test_corpus.py
tests/test_document.py
tests/test_metadata_creation.py
monodikit-0.0.10.dist-info/METADATA
monodikit-0.0.10.dist-info/WHEEL
monodikit-0.0.10.dist-info/top_level.txt
monodikit-0.0.10.dist-info/RECORD
