Metadata-Version: 2.1
Name: monodikit
Version: 0.0.10
Summary: MonodiKit is a Python library designed to facilitate the analysis and processing of medieval chant documents. It was specifically tailored to handle data in the monodi+ data format as edited by the Corpus Monodicum project. The library offers a set of classes that provide a wide range of functionalities, including parsing and processing of chant documents, exploring their hierarchical structure, managing metadata, generating musical notation, and extracting relevant information.
Home-page: https://github.com/timeipert/MonodiKit
Author: Tim Eipert & Fabian C. Moss
Author-email: tim.eipert@uni-wuerzburg.de
License: MIT
Classifier: 
Requires-Python: >=3.8
